missing_data_as_shadows/__init__.py
missing_data_as_shadows/core.py
missing_data_as_shadows-1.0.3.dist-info/METADATA
missing_data_as_shadows-1.0.3.dist-info/WHEEL
missing_data_as_shadows-1.0.3.dist-info/top_level.txt
missing_data_as_shadows-1.0.3.dist-info/RECORD
